xseis2/__init__.py
xseis2/h5cpp/.git
xseis2/h5stream.py
xseis2/include/gsl/gsl
xseis2/include/gsl/gsl_algorithm
xseis2/include/gsl/gsl_assert
xseis2/include/gsl/gsl_byte
xseis2/include/gsl/gsl_util
xseis2/include/gsl/multi_span
xseis2/include/gsl/pointers
xseis2/include/gsl/span
xseis2/include/gsl/string_span
xseis2/include/xseis2/beamform.h
xseis2/include/xseis2/core.h
xseis2/include/xseis2/hdf5.h
xseis2/include/xseis2/keygen.h
xseis2/include/xseis2/logger.h
xseis2/include/xseis2/npy.h
xseis2/include/xseis2/signal.h
xseis2/include/xseis2/workflows.h
xseis2/xchange.py
xseis2/xchange_workflow.py
xseis2/xflow.py
xseis2/xio.py
xseis2/xplot.py
xseis2/xplot3d.py
xseis2/xspy.pyx
xseis2/xsql.py
xseis2/xutil.py
xseis2/xspy.cpython-39-x86_64-linux-gnu.so
xseis2-0.2.4.dist-info/WHEEL
xseis2-0.2.4.dist-info/METADATA
xseis2-0.2.4.dist-info/RECORD
