Metadata-Version: 2.1
Name: xseis2
Version: 0.2.4
Summary: 
Author: Your Name
Author-email: you@example.com
Requires-Python: >=3.7.1,<3.11
Classifier: Programming Language :: Python :: 3
Classifier: Programming Language :: Python :: 3.10
Classifier: Programming Language :: Python :: 3.8
Classifier: Programming Language :: Python :: 3.9
Requires-Dist: Cython (>=0.29.27,<0.30.0)
Requires-Dist: obspy (>=1.2.2,<2.0.0)
Requires-Dist: setuptools (>=59.6.0,<60.0.0)
